ghit/__init__.py
ghit/__main__.py
ghit/args.py
ghit/branch_commands.py
ghit/common.py
ghit/error.py
ghit/gh.py
ghit/gh_formatting.py
ghit/gh_graphql.py
ghit/ghit.py
ghit/gitools.py
ghit/graphql.py
ghit/stack.py
ghit/stack_commands.py
ghit/styling.py
ghit/terminal.py
ghit/top_commands.py
ghit_smartptr-0.1.5.dist-info/METADATA
ghit_smartptr-0.1.5.dist-info/WHEEL
ghit_smartptr-0.1.5.dist-info/entry_points.txt
ghit_smartptr-0.1.5.dist-info/licenses/LICENSE
ghit_smartptr-0.1.5.dist-info/RECORD
