Metadata-Version: 2.3
Name: ghit-smartptr
Version: 0.1.5
Summary: ghit
Project-URL: Homepage, https://github.com/0x656b694d/ghit
Project-URL: Issues, https://github.com/0x656b694d/ghit/issues
Author-email: Michaël Petrov <smartptr@gmail.com>
License: MIT License
License-File: LICENSE
Classifier: License :: OSI Approved :: MIT License
Classifier: Operating System :: OS Independent
Classifier: Programming Language :: Python :: 3
Requires-Python: <4.0,>=3.9
Requires-Dist: pygit2
Requires-Dist: requests
Provides-Extra: testing
Requires-Dist: pygit2; extra == 'testing'
Requires-Dist: pytest; extra == 'testing'
Requires-Dist: requests; extra == 'testing'
